shoal/__init__.py
shoal/can_skip.py
shoal/cli.py
shoal/invoke_helpers.py
shoal/log.py
shoal/pretty_process.py
shoal/shell.py
shoal-1.0.0.dist-info/LICENSE
shoal-1.0.0.dist-info/WHEEL
shoal-1.0.0.dist-info/METADATA
shoal-1.0.0.dist-info/RECORD
