Metadata-Version: 2.1
Name: shoal
Version: 1.0.0
Summary: Opinionated CLI Task Runner built on Invoke
Home-page: https://github.com/kyleking/shoal
License: MIT
Author: Kyle King
Author-email: dev.act.kyle@gmail.com
Requires-Python: >=3.8.12,<4.0.0
Classifier: Development Status :: 4 - Beta
Classifier: License :: OSI Approved :: MIT License
Classifier: Operating System :: OS Independent
Classifier: Programming Language :: Python :: 3
Classifier: Programming Language :: Python :: 3.9
Classifier: Programming Language :: Python :: 3.10
Classifier: Programming Language :: Python :: 3.11
Classifier: Programming Language :: Python :: 3.10
Classifier: Programming Language :: Python :: 3.11
Classifier: Programming Language :: Python :: 3.8
Classifier: Programming Language :: Python :: 3.9
Requires-Dist: invoke (>=2.0.0)
Project-URL: Bug Tracker, https://github.com/kyleking/shoal/issues
Project-URL: Changelog, https://github.com/kyleking/shoal/blob/main/docs/docs/CHANGELOG.md
Project-URL: Documentation, https://shoal.kyleking.me
Project-URL: Repository, https://github.com/kyleking/shoal
